{
    "advt": false,
    "intensity_threshold": 32,
    "intensity_prob_threshold": 0.5,
    "alpha": 1,
    "gauss_kernel": 9,
    "prims": [10, 1020],
    "hc_param1": 100,
    "hc_param2": 30,
    "ed_th_low": 0,
    "ed_th_high": 127,
    "draw_param":
    {
        "hc_center":
        {
            "color": [0, 255, 0],
            "thick": 4
        },
        "hc_circle":
        {
            "color": [255, 0, 255],
            "thick": 2
        },
        "contur":
        {
            "color": [0, 255, 0],
            "thick": 2,
            "nest_color": [128, 128, 255]
        }
    }
}